astropixie_widgets/__init__.py
astropixie_widgets/config.py
astropixie_widgets/science.py
astropixie_widgets/visual.py
astropixie_widgets-0.1.8.dist-info/METADATA
astropixie_widgets-0.1.8.dist-info/RECORD
astropixie_widgets-0.1.8.dist-info/WHEEL
astropixie_widgets-0.1.8.dist-info/top_level.txt
