Metadata-Version: 2.1
Name: astropixie-widgets
Version: 0.1.8
Summary: LSST EPO 
Home-page: https://github.com/lsst-epo/vela/astropixie-widgets
Author: LSST EPO Team
Author-email: epo-team@lists.lsst.org
License: MIT
Platform: UNKNOWN
Requires-Dist: astropixie (==0.1.8)
Requires-Dist: astropy (<3.1,>=3.0.1)
Requires-Dist: astroquery (>=0.3.8)
Requires-Dist: bokeh (>=0.12.16)
Requires-Dist: numpy (<1.16,>=1.14.2)
Requires-Dist: pandas
Requires-Dist: pytest
Requires-Dist: scipy
